struct3.py
struct3-1.3.7.dist-info/LICENSE
struct3-1.3.7.dist-info/METADATA
struct3-1.3.7.dist-info/WHEEL
struct3-1.3.7.dist-info/top_level.txt
struct3-1.3.7.dist-info/RECORD
