Metadata-Version: 2.1
Name: struct3
Version: 1.3.7
Summary: Replacement for the standard struct lib
Home-page: UNKNOWN
Author: Loic M.Herry
Author-email: priv@octagonax.com
License: UNKNOWN
Platform: UNKNOWN
Classifier: Operating System :: OS Independent
Requires-Python: >=2.7
License-File: LICENSE
